dacota.py
dacota-0.1.1.dist-info/LICENCE.txt
dacota-0.1.1.dist-info/METADATA
dacota-0.1.1.dist-info/WHEEL
dacota-0.1.1.dist-info/top_level.txt
dacota-0.1.1.dist-info/RECORD
