Metadata-Version: 2.1
Name: dacota
Version: 0.1.1
Summary: Datategy Cohort Targeting : One-click discovery of diverse cohorts in your dataset with statistical guarantees
Home-page: https://github.com/datascientistunlu/dacota
Author: Dr. Eren Unlu
Author-email: eren.unlu@datategy.net
License: MIT
Keywords: Cohort,Cohortization,Data Analysis,Python 3,EDA
Classifier: Programming Language :: Python :: 3
Classifier: Programming Language :: Python :: 3.7
Classifier: Programming Language :: Python :: 3.8
Classifier: Programming Language :: Python :: 3.9
Classifier: Programming Language :: Python :: 3.10
Classifier: Topic :: Software Development :: Libraries :: Python Modules
Classifier: License :: OSI Approved :: MIT License
Classifier: Operating System :: OS Independent
Requires-Python: >=3
License-File: LICENCE.txt
Requires-Dist: numpy
Requires-Dist: pandas
Requires-Dist: scipy
